numpy_syncer/__init__.py
numpy_syncer/local_sync.py
numpy_syncer/numpy_sync.py
numpy_syncer-0.0.1.dist-info/METADATA
numpy_syncer-0.0.1.dist-info/WHEEL
numpy_syncer-0.0.1.dist-info/top_level.txt
numpy_syncer-0.0.1.dist-info/RECORD
